cognicli.py
cognicli-2.2.6.dist-info/licenses/LICENSE
cognicli-2.2.6.dist-info/METADATA
cognicli-2.2.6.dist-info/WHEEL
cognicli-2.2.6.dist-info/entry_points.txt
cognicli-2.2.6.dist-info/top_level.txt
cognicli-2.2.6.dist-info/RECORD
