Metadata-Version: 2.4
Name: cognicli
Version: 2.2.6
Summary: A premium, full-featured AI command line interface with Transformers and GGUF support
Home-page: https://github.com/cognicli/cognicli
Author: SynapseMoN
Maintainer: SynapseMoN
License: Apache-2.0
Project-URL: Homepage, https://github.com/cognicli/cognicli
Project-URL: Documentation, https://cognicli.readthedocs.io
Project-URL: Repository, https://github.com/cognicli/cognicli.git
Project-URL: Bug Reports, https://github.com/cognicli/cognicli/issues
Project-URL: Changelog, https://github.com/cognicli/cognicli/blob/main/CHANGELOG.md
Keywords: ai,llm,transformers,gguf,huggingface,cli,chatbot,language-model,artificial-intelligence,machine-learning,natural-language-processing,text-generation,chat,assistant,premium,robust,enhanced
Classifier: Development Status :: 5 - Production/Stable
Classifier: Intended Audience :: Developers
Classifier: Intended Audience :: Science/Research
Classifier: License :: OSI Approved :: Apache Software License
Classifier: Operating System :: OS Independent
Classifier: Programming Language :: Python :: 3
Classifier: Programming Language :: Python :: 3.8
Classifier: Programming Language :: Python :: 3.9
Classifier: Programming Language :: Python :: 3.10
Classifier: Programming Language :: Python :: 3.11
Classifier: Programming Language :: Python :: 3.12
Classifier: Topic :: Scientific/Engineering :: Artificial Intelligence
Classifier: Topic :: Software Development :: Libraries :: Python Modules
Classifier: Topic :: Utilities
Requires-Python: >=3.8
License-File: LICENSE
Requires-Dist: hf_xet
Requires-Dist: transformers>=4.35.0
Requires-Dist: huggingface-hub>=0.17.0
Requires-Dist: rich>=13.0.0
Requires-Dist: colorama>=0.4.6
Requires-Dist: requests>=2.31.0
Requires-Dist: psutil>=5.9.0
Requires-Dist: pyyaml>=6.0
Requires-Dist: numpy>=1.24.0
Requires-Dist: tokenizers>=0.14.0
Requires-Dist: accelerate>=0.24.0
Requires-Dist: sentencepiece>=0.1.99
Requires-Dist: protobuf>=4.24.0
Requires-Dist: ollama>=0.1.0
Provides-Extra: quantization
Requires-Dist: bitsandbytes>=0.41.0; extra == "quantization"
Provides-Extra: gguf
Requires-Dist: llama-cpp-python>=0.2.0; extra == "gguf"
Provides-Extra: gpu
Requires-Dist: bitsandbytes>=0.41.0; extra == "gpu"
Requires-Dist: llama-cpp-python[cublas]>=0.2.0; extra == "gpu"
Provides-Extra: metal
Requires-Dist: bitsandbytes>=0.41.0; extra == "metal"
Requires-Dist: llama-cpp-python[metal]>=0.2.0; extra == "metal"
Provides-Extra: full
Requires-Dist: bitsandbytes>=0.41.0; extra == "full"
Requires-Dist: llama-cpp-python>=0.2.0; extra == "full"
Requires-Dist: datasets>=2.14.0; extra == "full"
Requires-Dist: evaluate>=0.4.0; extra == "full"
Requires-Dist: wandb>=0.15.0; extra == "full"
Provides-Extra: dev
Requires-Dist: pytest>=7.0.0; extra == "dev"
Requires-Dist: pytest-cov>=4.0.0; extra == "dev"
Requires-Dist: black>=23.0.0; extra == "dev"
Requires-Dist: flake8>=6.0.0; extra == "dev"
Requires-Dist: mypy>=1.0.0; extra == "dev"
Requires-Dist: pre-commit>=3.0.0; extra == "dev"
Dynamic: home-page
Dynamic: license-file
Dynamic: requires-python
